---
layout: post
title:  "volatile的是与非"
date:   2017-01-23
excerpt: "volatile关键字的一些特性与线程安全"
tag:
- volatile
- java
- 多线程
- concurrent
comments: true
---
### volatile关键字所做的事情
被volatile修饰的属性，在修改属性的值的时候，会增加一个内存屏障，将包括该属性在内的前面所有修改的属性刷新CPU缓存，做到属性的变化对其他线程可见。

### volatile关键字的用处
保证属性的安全，即属性的任何变化都能够做到及时对其他线程可见.

### volatile不等同于线程安全
由于一个线程会将临界变量的值压入线程栈，类似在线程栈中对临界属性做了备份，所以即使临界属性时时保证为最新的值，但无法更改线程栈中的备份，所以也就无法做到线程安全。

下面来看一个具体示例

__java源码:__
{% highlight java %}
{% raw %}
public class T2 {


    private Integer i = 1;

    public void test3() {
        i = i + 2;
    }
}
{% endraw %}
{% endhighlight %}
__反汇编:__
{% highlight java %}
{% raw %}
Compiled from "T2.java"
public class test.T2 {
  public test.T2();
    Code:
       0: aload_0
       1: invokespecial #1                  // Method java/lang/Object."<init>":()V
       4: aload_0
       5: iconst_1
       6: invokestatic  #2                  // Method java/lang/Integer.valueOf:(I)Ljava/lang/Integer;
       9: putfield      #3                  // Field i:Ljava/lang/Integer;
      12: return

  public void test3();
    Code:
       0: aload_0
       1: aload_0
       2: getfield      #3                  // Field i:Ljava/lang/Integer; -- 将属性i的引用压入栈顶
       5: invokevirtual #4                  // Method java/lang/Integer.intValue:()I --i的引用出栈并调用intValue()方法，并将结果压入栈顶
       8: iconst_2
       9: iadd
      10: invokestatic  #2                  // Method java/lang/Integer.valueOf:(I)Ljava/lang/Integer;
      13: putfield      #3                  // Field i:Ljava/lang/Integer;
      16: return
}
{% endraw %}
{% endhighlight %}
可以看出，在```test3```方法中, 虚拟机会拿到临界变量```i```的值，并且将```i```的值压入栈顶，后续计算操作使用的是线程栈中的值进行操作。

#### 结论
所以，volatile可以保证属性安全，但并非保证线程安全。

## 说明
博主是个水货，如果写的不对的地方欢迎大家指出来。
